tos_decrator/__init__.py
tos_decrator/tos_decrator.py
tos_decrator-0.3.dist-info/METADATA
tos_decrator-0.3.dist-info/WHEEL
tos_decrator-0.3.dist-info/top_level.txt
tos_decrator-0.3.dist-info/RECORD
