Metadata-Version: 2.1
Name: tos-decrator
Version: 0.3
Summary: A simple tos decrator to download file,process and upload
Author: Yukun Li
Author-email: liyukun@mathmagical.com
Requires-Dist: tos
